cellwrapper/__init__.py
cellwrapper/__main__.py
cellwrapper/cellwrapper.py
cellwrapper-0.1.4.dist-info/METADATA
cellwrapper-0.1.4.dist-info/WHEEL
cellwrapper-0.1.4.dist-info/entry_points.txt
cellwrapper-0.1.4.dist-info/top_level.txt
cellwrapper-0.1.4.dist-info/RECORD
