Metadata-Version: 2.1
Name: cellwrapper
Version: 0.1.4
Summary: A python wrapper for fast and parallel processing of cellranger runs
Home-page: https://github.com/scfurl/cellwrapper.git
Author: Scott Furlan
Author-email: scottfurlan@gmail.com
License: UNKNOWN
Platform: UNKNOWN
Classifier: Programming Language :: Python :: 3
Classifier: License :: OSI Approved :: MIT License
Classifier: Operating System :: OS Independent
Requires-Python: >=2.5
Requires-Dist: six (>=1)
